macrostrat/dinosaur/__init__.py
macrostrat/dinosaur/upgrade_cluster/__init__.py
macrostrat/dinosaur/upgrade_cluster/describe.py
macrostrat/dinosaur/upgrade_cluster/restore.py
macrostrat/dinosaur/upgrade_cluster/utils.py
macrostrat_dinosaur-3.2.0.dist-info/METADATA
macrostrat_dinosaur-3.2.0.dist-info/WHEEL
macrostrat_dinosaur-3.2.0.dist-info/RECORD
