Metadata-Version: 2.1
Name: macrostrat.dinosaur
Version: 3.2.0
Summary: Diff-based database migrations
Author: Daven Quinn
Author-email: dev@davenquinn.com
Requires-Python: >=3.10,<4.0
Classifier: Programming Language :: Python :: 3
Classifier: Programming Language :: Python :: 3.10
Classifier: Programming Language :: Python :: 3.11
Classifier: Programming Language :: Python :: 3.12
Requires-Dist: SQLAlchemy (>=2.0.0,<3.0.0)
Requires-Dist: docker (>=7.0.0,<8.0.0)
Requires-Dist: macrostrat.database (>=3.4.1,<4.0.0)
Requires-Dist: macrostrat.utils (>=1.2.1,<2.0.0)
Requires-Dist: migra (>=3.0.1621480950,<4.0.0)
Requires-Dist: psycopg2-binary (>=2.9.1,<3.0.0)
Requires-Dist: schemainspect (>=3.0.1616029793,<4.0.0)
